{
    "config": {
        "policyName": {
         "value": "storageAccountFileEncryptionPolicy"
       },
        "policyDisplayName": {
         "value": ""
       },
        "policyDescription": {
         "value": ""
        },
       "assignmentName": {
        "value": "storageAccountFileEncryptionAssignment"
       },
        "assignmentDisplayName": {
         "value": ""
       },
        "assignmentDescription": {
         "value": ""
        },
        "policySetName": {
            "value": ""
        }
    }
}